configpro/__init__.py
configpro-0.0.1.dist-info/LICENSE.txt
configpro-0.0.1.dist-info/METADATA
configpro-0.0.1.dist-info/WHEEL
configpro-0.0.1.dist-info/entry_points.txt
configpro-0.0.1.dist-info/top_level.txt
configpro-0.0.1.dist-info/RECORD
